SuperfacilityAPI/SuperfacilityAPI.py
SuperfacilityAPI/SuperfacilityAccessToken.py
SuperfacilityAPI/__init__.py
SuperfacilityAPI/api_version.py
SuperfacilityAPI/error_warnings.py
SuperfacilityAPI/nersc_systems.py
SuperfacilityConnector-0.2.0.data/scripts/sfapi
SuperfacilityConnector-0.2.0.dist-info/LICENSE
SuperfacilityConnector-0.2.0.dist-info/METADATA
SuperfacilityConnector-0.2.0.dist-info/WHEEL
SuperfacilityConnector-0.2.0.dist-info/top_level.txt
SuperfacilityConnector-0.2.0.dist-info/RECORD
