Metadata-Version: 2.1
Name: SuperfacilityConnector
Version: 0.2.0
Summary: Connector API NERSC Superfacility
Home-page: https://github.com/tylern4/superfacilityConnector
Author: Nick Tyler
Author-email: tylern@lbl.gov
License: UNKNOWN
Platform: UNKNOWN
Classifier: Programming Language :: Python :: 3
Classifier: Operating System :: OS Independent
Classifier: Topic :: Scientific/Engineering
Requires-Python: >=3.5
License-File: LICENSE
Requires-Dist: authlib
Requires-Dist: requests
Requires-Dist: click
